similarity/__init__.py
similarity/cosine.py
similarity/cosine_test.py
similarity/damerau.py
similarity/damerau_test.py
similarity/jaccard.py
similarity/jaccard_test.py
similarity/jarowinkler.py
similarity/jarowinkler_test.py
similarity/levenshtein.py
similarity/levenshtein_test.py
similarity/longest_common_subsequence.py
similarity/longest_common_subsequence_test.py
similarity/metric_lcs.py
similarity/metric_lcs_test.py
similarity/ngram.py
similarity/ngram_test.py
similarity/normalized_levenshtein.py
similarity/normalized_levenshtein_test.py
similarity/optimal_string_alignment.py
similarity/optimal_string_alignment_test.py
similarity/qgram.py
similarity/qgram_test.py
similarity/shingle_based.py
similarity/similarity.py
similarity/sorensen_dice.py
similarity/sorensen_dice_test.py
similarity/string_distance.py
similarity/string_similarity.py
similarity/weighted_levenshtein.py
similarity/weighted_levenshtein_test.py
strsim-0.0.1.dist-info/METADATA
strsim-0.0.1.dist-info/RECORD
strsim-0.0.1.dist-info/WHEEL
strsim-0.0.1.dist-info/top_level.txt
