Metadata-Version: 2.1
Name: strsim
Version: 0.0.1
Summary: A library implementing different string similarity and distance measures
Home-page: https://github.com/luozhouyang/python-string-similarity
Author: ZhouYang Luo
Author-email: stupidme.me.lzy@gmail.com
License: MIT License
Platform: UNKNOWN
Classifier: Programming Language :: Python :: 3
Classifier: License :: OSI Approved :: MIT License
Classifier: Operating System :: OS Independent
Requires-Dist: numpy (>=1.12.0)
